git_lfs/__init__.py
git_lfs/__main__.py
git_lfs/utils.py
git_lfs-1.6.dist-info/METADATA
git_lfs-1.6.dist-info/WHEEL
git_lfs-1.6.dist-info/top_level.txt
git_lfs-1.6.dist-info/RECORD
