Metadata-Version: 2.1
Name: git-lfs
Version: 1.6
Summary: A lightweight Git Large File Storage fetcher
Home-page: https://github.com/liberapay/git-lfs-fetch.py
Author: Changaco
Author-email: changaco@changaco.oy.lc
License: CC0
Keywords: git lfs
Platform: UNKNOWN
